pykzee/__init__.py
pykzee/inspector/InspectorPlugin.py
pykzee/inspector/__init__.py
pykzee/inspector/__version__.py
pykzee/inspector/resources/index.html
pykzee/inspector/resources/static/inspector.js
pykzee/inspector/resources/static/licenses.txt
pykzee/inspector/resources/static/style.css
pykzee_inspector-0.1.0.dist-info/LICENSE
pykzee_inspector-0.1.0.dist-info/METADATA
pykzee_inspector-0.1.0.dist-info/WHEEL
pykzee_inspector-0.1.0.dist-info/top_level.txt
pykzee_inspector-0.1.0.dist-info/RECORD
