Metadata-Version: 2.1
Name: pykzee-inspector
Version: 0.1.0
Summary: Web interface for inspecting the Pykzee state
Home-page: https://github.com/spacedentist/pykzee-inspector
Author: Sven Over
Author-email: sp@cedenti.st
License: MIT
Download-URL: https://github.com/spacedentist/pykzee-inspector/archive/0.1.0.tar.gz
Platform: UNKNOWN
Requires-Dist: aiohttp
Requires-Dist: pykzee
